wwttoolbox/__init__.py
wwttoolbox/conversion/__init__.py
wwttoolbox/conversion/time_conversion.py
wwttoolbox/conversion/time_expression_parser.py
wwttoolbox/conversion/unit_conversion.py
wwttoolbox/nc/__init__.py
wwttoolbox/nc/nc_mask_utils.py
wwttoolbox/nc/nc_tool.py
wwttoolbox/nc/nc_utils.py
wwttoolbox/nc/nc_wet_tool.py
wwttoolbox/qaqc/__init__.py
wwttoolbox/qaqc/anomaly_detection/__init__.py
wwttoolbox/qaqc/anomaly_detection/anomaly_detection_algorithm.py
wwttoolbox/qaqc/anomaly_detection/anomaly_detection_config.py
wwttoolbox/qaqc/anomaly_detection/anomaly_detection_validation.py
wwttoolbox/qaqc/anomaly_detection/quality_codes.py
wwttoolbox/qaqc/anomaly_detection/rolling_window.py
wwttoolbox/transformers/__init__.py
wwttoolbox/transformers/swat/__init__.py
wwttoolbox/transformers/swat/cast_functions.py
wwttoolbox/transformers/swat/csv_2_netcdf.py
wwttoolbox/transformers/swat/csv_2_netcdf_no_gis_dim.py
wwttoolbox/transformers/swat/csv_reader.py
wwttoolbox/transformers/swat/swat_aquifer_deep_removal.py
wwttoolbox/transformers/swat/swat_data_column.py
wwttoolbox/transformers/swat/swat_write_cli_files.py
wwttoolbox/transformers/swat/swat_write_station_data.py
wwttoolbox/transformers/swat/swat_write_time_sim.py
wwttoolbox/transformers/wet/__init__.py
wwttoolbox/transformers/wet/dat_column.py
wwttoolbox/transformers/wet/wet_write_dat.py
wwttoolbox/yaml/__init__.py
wwttoolbox/yaml/yaml_editor.py
wwttoolbox-0.17.1.dist-info/licenses/LICENSE
wwttoolbox-0.17.1.dist-info/METADATA
wwttoolbox-0.17.1.dist-info/WHEEL
wwttoolbox-0.17.1.dist-info/top_level.txt
wwttoolbox-0.17.1.dist-info/RECORD
