Metadata-Version: 2.4
Name: wwttoolbox
Version: 0.17.1
Summary: WaterWebTool toolbox for common tasks in hydrology and water resources management
Author-email: WaterWebTools <info@waterwebtools.com>
License-File: LICENSE
Requires-Dist: netcdf4
Requires-Dist: ruamel.yaml
Provides-Extra: dev
Requires-Dist: pytest; extra == "dev"
Provides-Extra: qaqc
Requires-Dist: pandas; extra == "qaqc"
Requires-Dist: scipy; extra == "qaqc"
Requires-Dist: numpy; extra == "qaqc"
Provides-Extra: qaqc-validation
Requires-Dist: plotly; extra == "qaqc-validation"
Dynamic: license-file
